Lab_0/counter.v
// Design
module counter(
    input wire clk,
    input wire rst,
    output reg a0,
    output reg a1,
    output reg a2,
    output reg a3
);

    always @(posedge clk) begin
        if (rst) begin
            a0 <= 1'b0;
            a1 <= 1'b0;
            a2 <= 1'b0;
            a3 <= 1'b0;
        end
        else begin
            a0 <= ~a0;
            a1 <= a0 ^ a1;
            a2 <= (a0 & a1) ^ a2;
            a3 <= (a0 & a1 & a2) ^ a3;
        end
    end

endmodule

Lab_0/counter_tb.v
// Testbench
`timescale 10ns/1ns

module counter_tb;
    reg clk;
    reg rst;
    wire a0;
    wire a1;
    wire a2;
    wire a3;

    counter my_counter(clk, rst, a0, a1, a2, a3);

    initial begin
        $dumpfile("wave.vcd");
        $dumpvars(0, counter_tb);

        clk = 0;
        rst = 1;
        #1
        rst = 0;

        #20 $finish;
    end

    always begin
        #0.5 clk = ~clk;
    end
endmodule

Lab_0/wave.vcd
$date
	Thu Jan 16 11:10:42 2025
$end
$version
	Icarus Verilog
$end
$timescale
	1ns
$end
$scope module counter_tb $end
$var wire 1 ! a3 $end
$var wire 1 " a2 $end
$var wire 1 # a1 $end
$var wire 1 $ a0 $end
$var reg 1 % clk $end
$var reg 1 & rst $end
$scope module my_counter $end
$var wire 1 % clk $end
$var wire 1 & rst $end
$var reg 1 $ a0 $end
$var reg 1 # a1 $end
$var reg 1 " a2 $end
$var reg 1 ! a3 $end
$upscope $end
$upscope $end
$enddefinitions $end
$comment Show the parameter values. $end
$dumpall
$end
#0
$dumpvars
1&
0%
x$
x#
x"
x!
$end
#5
0!
0"
0#
0$
1%
#10
0%
0&
#15
1$
1%
#20
0%
#25
1#
0$
1%
#30
0%
#35
1$
1%
#40
0%
#45
1"
0#
0$
1%
#50
0%
#55
1$
1%
#60
0%
#65
1#
0$
1%
#70
0%
#75
1$
1%
#80
0%
#85
1!
0"
0#
0$
1%
#90
0%
#95
1$
1%
#100
0%
#105
1#
0$
1%
#110
0%
#115
1$
1%
#120
0%
#125
1"
0#
0$
1%
#130
0%
#135
1$
1%
#140
0%
#145
1#
0$
1%
#150
0%
#155
1$
1%
#160
0%
#165
0!
0"
0#
0$
1%
#170
0%
#175
1$
1%
#180
0%
#185
1#
0$
1%
#190
0%
#195
1$
1%
#200
0%
#205
1"
0#
0$
1%
